[
{
"timestamp" : 1621958987587,
"event_id" : "application_start",
"info" : "Anyaroth",
"attributes" : {}
},
{
"timestamp" : 1621958987587,
"event_id" : "seed",
"info" : "",
"attributes" : {
"seed" : "1621958987"
}
},
{
"timestamp" : 1621959011592,
"event_id" : "input",
"info" : "",
"attributes" : {
"button" : "1",
"buttonState" : "0",
"key" : "779",
"keyRepeat" : "0",
"step" : "0",
"type" : "1026",
"xMouse" : "194",
"yMouse" : "181"
}
},
{
"timestamp" : 1621959011614,
"event_id" : "posScreen",
"info" : "",
"attributes" : {
"xMouseScreen" : "779",
"yMouseScreen" : "724"
}
},
{
"timestamp" : 1621959011617,
"event_id" : "posScreen",
"info" : "",
"attributes" : {
"xMouseScreen" : "779",
"yMouseScreen" : "724"
}
},
{
"timestamp" : 1621959011620,
"event_id" : "posScreen",
"info" : "",
"attributes" : {
"xMouseScreen" : "779",
"yMouseScreen" : "724"
}
},
{
"timestamp" : 1621959011623,
"event_id" : "posScreen",
"info" : "",
"attributes" : {
"xMouseScreen" : "779",
"yMouseScreen" : "724"
}
},
{
"timestamp" : 1621959011663,
"event_id" : "posScreen",
"info" : "",
"attributes" : {
"xMouseScreen" : "779",
"yMouseScreen" : "724"
}
},
{
"timestamp" : 1621959011743,
"event_id" : "posScreen",
"info" : "",
"attributes" : {
"xMouseScreen" : "779",
"yMouseScreen" : "724"
}
},
{
"timestamp" : 1621959011825,
"event_id" : "posScreen",
"info" : "",
"attributes" : {
"xMouseScreen" : "779",
"yMouseScreen" : "724"
}
},
{
"timestamp" : 1621959011904,
"event_id" : "posScreen",
"info" : "",
"attributes" : {
"xMouseScreen" : "779",
"yMouseScreen" : "724"
}
},
{
"timestamp" : 1621959011984,
"event_id" : "posScreen",
"info" : "",
"attributes" : {
"xMouseScreen" : "779",
"yMouseScreen" : "724"
}
},
{
"timestamp" : 1621959012064,
"event_id" : "posScreen",
"info" : "",
"attributes" : {
"xMouseScreen" : "779",
"yMouseScreen" : "724"
}
},
{
"timestamp" : 1621959012144,
"event_id" : "posScreen",
"info" : "",
"attributes" : {
"xMouseScreen" : "779",
"yMouseScreen" : "724"
}
},
{
"timestamp" : 1621959012226,
"event_id" : "posScreen",
"info" : "",
"attributes" : {
"xMouseScreen" : "828",
"yMouseScreen" : "707"
}
},
{
"timestamp" : 1621959012303,
"event_id" : "posScreen",
"info" : "",
"attributes" : {
"xMouseScreen" : "931",
"yMouseScreen" : "621"
}
},
{
"timestamp" : 1621959012383,
"event_id" : "posScreen",
"info" : "",
"attributes" : {
"xMouseScreen" : "1027",
"yMouseScreen" : "530"
}
},
{
"timestamp" : 1621959012465,
"event_id" : "posScreen",
"info" : "",
"attributes" : {
"xMouseScreen" : "1047",
"yMouseScreen" : "515"
}
},
{
"timestamp" : 1621959012543,
"event_id" : "posScreen",
"info" : "",
"attributes" : {
"xMouseScreen" : "1152",
"yMouseScreen" : "490"
}
},
{
"timestamp" : 1621959012623,
"event_id" : "posScreen",
"info" : "",
"attributes" : {
"xMouseScreen" : "1292",
"yMouseScreen" : "473"
}
},
{
"timestamp" : 1621959012704,
"event_id" : "posScreen",
"info" : "",
"attributes" : {
"xMouseScreen" : "1367",
"yMouseScreen" : "469"
}
},
{
"timestamp" : 1621959012786,
"event_id" : "posScreen",
"info" : "",
"attributes" : {
"xMouseScreen" : "1421",
"yMouseScreen" : "464"
}
},
{
"timestamp" : 1621959012864,
"event_id" : "posScreen",
"info" : "",
"attributes" : {
"xMouseScreen" : "1453",
"yMouseScreen" : "455"
}
},
{
"timestamp" : 1621959012864,
"event_id" : "playerPos",
"info" : "",
"attributes" : {
"x" : "6.000000",
"y" : "18.195004"
}
},
{
"timestamp" : 1621959012943,
"event_id" : "posScreen",
"info" : "",
"attributes" : {
"xMouseScreen" : "1507",
"yMouseScreen" : "447"
}
},
{
"timestamp" : 1621959013023,
"event_id" : "posScreen",
"info" : "",
"attributes" : {
"xMouseScreen" : "1589",
"yMouseScreen" : "458"
}
},
{
"timestamp" : 1621959013105,
"event_id" : "posScreen",
"info" : "",
"attributes" : {
"xMouseScreen" : "1627",
"yMouseScreen" : "463"
}
},
{
"timestamp" : 1621959013183,
"event_id" : "posScreen",
"info" : "",
"attributes" : {
"xMouseScreen" : "1646",
"yMouseScreen" : "465"
}
},
{
"timestamp" : 1621959013265,
"event_id" : "posScreen",
"info" : "",
"attributes" : {
"xMouseScreen" : "1667",
"yMouseScreen" : "466"
}
},
{
"timestamp" : 1621959013342,
"event_id" : "posScreen",
"info" : "",
"attributes" : {
"xMouseScreen" : "1678",
"yMouseScreen" : "460"
}
},
{
"timestamp" : 1621959013378,
"event_id" : "input",
"info" : "",
"attributes" : {
"button" : "1",
"buttonState" : "1",
"key" : "1678",
"keyRepeat" : "0",
"step" : "132",
"type" : "1025",
"xMouse" : "419",
"yMouse" : "115"
}
},
{
"timestamp" : 1621959013425,
"event_id" : "posScreen",
"info" : "",
"attributes" : {
"xMouseScreen" : "1678",
"yMouseScreen" : "460"
}
},
{
"timestamp" : 1621959013475,
"event_id" : "input",
"info" : "",
"attributes" : {
"button" : "1",
"buttonState" : "0",
"key" : "1678",
"keyRepeat" : "0",
"step" : "138",
"type" : "1026",
"xMouse" : "419",
"yMouse" : "115"
}
},
{
"timestamp" : 1621959013503,
"event_id" : "posScreen",
"info" : "",
"attributes" : {
"xMouseScreen" : "1678",
"yMouseScreen" : "460"
}
},
{
"timestamp" : 1621959013585,
"event_id" : "posScreen",
"info" : "",
"attributes" : {
"xMouseScreen" : "1678",
"yMouseScreen" : "460"
}
},
{
"timestamp" : 1621959013663,
"event_id" : "posScreen",
"info" : "",
"attributes" : {
"xMouseScreen" : "1678",
"yMouseScreen" : "460"
}
},
{
"timestamp" : 1621959013745,
"event_id" : "posScreen",
"info" : "",
"attributes" : {
"xMouseScreen" : "1678",
"yMouseScreen" : "460"
}
},
{
"timestamp" : 1621959013824,
"event_id" : "posScreen",
"info" : "",
"attributes" : {
"xMouseScreen" : "1678",
"yMouseScreen" : "460"
}
},
{
"timestamp" : 1621959013891,
"event_id" : "input",
"info" : "",
"attributes" : {
"button" : "1",
"buttonState" : "1",
"key" : "1678",
"keyRepeat" : "0",
"step" : "164",
"type" : "1025",
"xMouse" : "419",
"yMouse" : "115"
}
},
{
"timestamp" : 1621959013905,
"event_id" : "posScreen",
"info" : "",
"attributes" : {
"xMouseScreen" : "1678",
"yMouseScreen" : "460"
}
},
{
"timestamp" : 1621959013978,
"event_id" : "input",
"info" : "",
"attributes" : {
"button" : "1",
"buttonState" : "0",
"key" : "1678",
"keyRepeat" : "0",
"step" : "169",
"type" : "1026",
"xMouse" : "419",
"yMouse" : "115"
}
},
{
"timestamp" : 1621959013982,
"event_id" : "posScreen",
"info" : "",
"attributes" : {
"xMouseScreen" : "1678",
"yMouseScreen" : "460"
}
},
{
"timestamp" : 1621959014063,
"event_id" : "posScreen",
"info" : "",
"attributes" : {
"xMouseScreen" : "1678",
"yMouseScreen" : "460"
}
},
{
"timestamp" : 1621959014133,
"event_id" : "input",
"info" : "",
"attributes" : {
"button" : "1",
"buttonState" : "1",
"key" : "1678",
"keyRepeat" : "0",
"step" : "179",
"type" : "1025",
"xMouse" : "419",
"yMouse" : "115"
}
},
{
"timestamp" : 1621959014144,
"event_id" : "posScreen",
"info" : "",
"attributes" : {
"xMouseScreen" : "1678",
"yMouseScreen" : "460"
}
},
{
"timestamp" : 1621959014214,
"event_id" : "input",
"info" : "",
"attributes" : {
"button" : "1",
"buttonState" : "0",
"key" : "1678",
"keyRepeat" : "0",
"step" : "184",
"type" : "1026",
"xMouse" : "419",
"yMouse" : "115"
}
},
{
"timestamp" : 1621959014225,
"event_id" : "posScreen",
"info" : "",
"attributes" : {
"xMouseScreen" : "1678",
"yMouseScreen" : "460"
}
},
{
"timestamp" : 1621959014304,
"event_id" : "posScreen",
"info" : "",
"attributes" : {
"xMouseScreen" : "1678",
"yMouseScreen" : "460"
}
},
{
"timestamp" : 1621959014335,
"event_id" : "input",
"info" : "",
"attributes" : {
"button" : "1",
"buttonState" : "1",
"key" : "1678",
"keyRepeat" : "0",
"step" : "191",
"type" : "1025",
"xMouse" : "419",
"yMouse" : "115"
}
},
{
"timestamp" : 1621959014384,
"event_id" : "posScreen",
"info" : "",
"attributes" : {
"xMouseScreen" : "1678",
"yMouseScreen" : "460"
}
},
{
"timestamp" : 1621959014406,
"event_id" : "input",
"info" : "",
"attributes" : {
"button" : "1",
"buttonState" : "0",
"key" : "1678",
"keyRepeat" : "0",
"step" : "196",
"type" : "1026",
"xMouse" : "419",
"yMouse" : "115"
}
},
{
"timestamp" : 1621959014463,
"event_id" : "posScreen",
"info" : "",
"attributes" : {
"xMouseScreen" : "1678",
"yMouseScreen" : "460"
}
},
{
"timestamp" : 1621959014463,
"event_id" : "playerPos",
"info" : "",
"attributes" : {
"x" : "6.000000",
"y" : "18.195004"
}
},
{
"timestamp" : 1621959014545,
"event_id" : "posScreen",
"info" : "",
"attributes" : {
"xMouseScreen" : "1678",
"yMouseScreen" : "460"
}
},
{
"timestamp" : 1621959014602,
"event_id" : "input",
"info" : "",
"attributes" : {
"button" : "1",
"buttonState" : "1",
"key" : "1678",
"keyRepeat" : "0",
"step" : "208",
"type" : "1025",
"xMouse" : "419",
"yMouse" : "115"
}
},
{
"timestamp" : 1621959014625,
"event_id" : "posScreen",
"info" : "",
"attributes" : {
"xMouseScreen" : "1678",
"yMouseScreen" : "460"
}
},
{
"timestamp" : 1621959014705,
"event_id" : "posScreen",
"info" : "",
"attributes" : {
"xMouseScreen" : "1678",
"yMouseScreen" : "460"
}
},
{
"timestamp" : 1621959014715,
"event_id" : "input",
"info" : "",
"attributes" : {
"button" : "1",
"buttonState" : "0",
"key" : "1678",
"keyRepeat" : "0",
"step" : "215",
"type" : "1026",
"xMouse" : "419",
"yMouse" : "115"
}
},
{
"timestamp" : 1621959014783,
"event_id" : "posScreen",
"info" : "",
"attributes" : {
"xMouseScreen" : "1678",
"yMouseScreen" : "460"
}
},
{
"timestamp" : 1621959014864,
"event_id" : "posScreen",
"info" : "",
"attributes" : {
"xMouseScreen" : "1678",
"yMouseScreen" : "460"
}
},
{
"timestamp" : 1621959014943,
"event_id" : "posScreen",
"info" : "",
"attributes" : {
"xMouseScreen" : "1678",
"yMouseScreen" : "460"
}
},
{
"timestamp" : 1621959014979,
"event_id" : "input",
"info" : "",
"attributes" : {
"button" : "1",
"buttonState" : "1",
"key" : "1678",
"keyRepeat" : "0",
"step" : "232",
"type" : "1025",
"xMouse" : "419",
"yMouse" : "115"
}
},
{
"timestamp" : 1621959015022,
"event_id" : "posScreen",
"info" : "",
"attributes" : {
"xMouseScreen" : "1678",
"yMouseScreen" : "460"
}
},
{
"timestamp" : 1621959015068,
"event_id" : "input",
"info" : "",
"attributes" : {
"button" : "1",
"buttonState" : "0",
"key" : "1678",
"keyRepeat" : "0",
"step" : "237",
"type" : "1026",
"xMouse" : "419",
"yMouse" : "115"
}
},
{
"timestamp" : 1621959015071,
"event_id" : "enemyDeath",
"info" : "",
"attributes" : {
"id" : "0",
"step" : "237",
"x" : "55.238998",
"y" : "13.338750"
}
},
{
"timestamp" : 1621959015071,
"event_id" : "drop",
"info" : "",
"attributes" : {
"type" : "coin"
}
},
{
"timestamp" : 1621959015104,
"event_id" : "posScreen",
"info" : "",
"attributes" : {
"xMouseScreen" : "1678",
"yMouseScreen" : "460"
}
},
{
"timestamp" : 1621959015184,
"event_id" : "posScreen",
"info" : "",
"attributes" : {
"xMouseScreen" : "1678",
"yMouseScreen" : "460"
}
},
{
"timestamp" : 1621959015262,
"event_id" : "posScreen",
"info" : "",
"attributes" : {
"xMouseScreen" : "1678",
"yMouseScreen" : "460"
}
},
{
"timestamp" : 1621959015344,
"event_id" : "posScreen",
"info" : "",
"attributes" : {
"xMouseScreen" : "1678",
"yMouseScreen" : "460"
}
},
{
"timestamp" : 1621959015424,
"event_id" : "posScreen",
"info" : "",
"attributes" : {
"xMouseScreen" : "1678",
"yMouseScreen" : "460"
}
},
{
"timestamp" : 1621959015502,
"event_id" : "posScreen",
"info" : "",
"attributes" : {
"xMouseScreen" : "1678",
"yMouseScreen" : "460"
}
},
{
"timestamp" : 1621959015584,
"event_id" : "posScreen",
"info" : "",
"attributes" : {
"xMouseScreen" : "1678",
"yMouseScreen" : "460"
}
},
{
"timestamp" : 1621959015663,
"event_id" : "posScreen",
"info" : "",
"attributes" : {
"xMouseScreen" : "1678",
"yMouseScreen" : "460"
}
},
{
"timestamp" : 1621959015743,
"event_id" : "posScreen",
"info" : "",
"attributes" : {
"xMouseScreen" : "1678",
"yMouseScreen" : "460"
}
},
{
"timestamp" : 1621959015824,
"event_id" : "posScreen",
"info" : "",
"attributes" : {
"xMouseScreen" : "1678",
"yMouseScreen" : "460"
}
},
{
"timestamp" : 1621959015904,
"event_id" : "posScreen",
"info" : "",
"attributes" : {
"xMouseScreen" : "1678",
"yMouseScreen" : "460"
}
},
{
"timestamp" : 1621959015983,
"event_id" : "posScreen",
"info" : "",
"attributes" : {
"xMouseScreen" : "1678",
"yMouseScreen" : "460"
}
},
{
"timestamp" : 1621959016063,
"event_id" : "posScreen",
"info" : "",
"attributes" : {
"xMouseScreen" : "1678",
"yMouseScreen" : "460"
}
},
{
"timestamp" : 1621959016063,
"event_id" : "playerPos",
"info" : "",
"attributes" : {
"x" : "6.000000",
"y" : "18.195004"
}
},
{
"timestamp" : 1621959016145,
"event_id" : "posScreen",
"info" : "",
"attributes" : {
"xMouseScreen" : "1678",
"yMouseScreen" : "460"
}
},
{
"timestamp" : 1621959016224,
"event_id" : "posScreen",
"info" : "",
"attributes" : {
"xMouseScreen" : "1678",
"yMouseScreen" : "460"
}
},
{
"timestamp" : 1621959016304,
"event_id" : "posScreen",
"info" : "",
"attributes" : {
"xMouseScreen" : "1678",
"yMouseScreen" : "460"
}
},
{
"timestamp" : 1621959016383,
"event_id" : "posScreen",
"info" : "",
"attributes" : {
"xMouseScreen" : "1678",
"yMouseScreen" : "460"
}
},
{
"timestamp" : 1621959016465,
"event_id" : "posScreen",
"info" : "",
"attributes" : {
"xMouseScreen" : "1678",
"yMouseScreen" : "460"
}
},
{
"timestamp" : 1621959016542,
"event_id" : "posScreen",
"info" : "",
"attributes" : {
"xMouseScreen" : "1678",
"yMouseScreen" : "460"
}
},
{
"timestamp" : 1621959016624,
"event_id" : "posScreen",
"info" : "",
"attributes" : {
"xMouseScreen" : "1678",
"yMouseScreen" : "460"
}
},
{
"timestamp" : 1621959016703,
"event_id" : "posScreen",
"info" : "",
"attributes" : {
"xMouseScreen" : "1678",
"yMouseScreen" : "460"
}
},
{
"timestamp" : 1621959016783,
"event_id" : "posScreen",
"info" : "",
"attributes" : {
"xMouseScreen" : "1678",
"yMouseScreen" : "460"
}
},
{
"timestamp" : 1621959016865,
"event_id" : "posScreen",
"info" : "",
"attributes" : {
"xMouseScreen" : "1678",
"yMouseScreen" : "460"
}
},
{
"timestamp" : 1621959016943,
"event_id" : "posScreen",
"info" : "",
"attributes" : {
"xMouseScreen" : "1678",
"yMouseScreen" : "460"
}
},
{
"timestamp" : 1621959016999,
"event_id" : "input",
"info" : "",
"attributes" : {
"button" : "41",
"buttonState" : "0",
"key" : "27",
"keyRepeat" : "0",
"step" : "358",
"type" : "768",
"xMouse" : "419",
"yMouse" : "115"
}
},
{
"timestamp" : 1621959018602,
"event_id" : "application_ends",
"info" : "Anyaroth",
"attributes" : {}
}
]